sk_dsp_comm/pyaudio_helper/__init__.py
sk_dsp_comm/pyaudio_helper/__version__.py
sk_dsp_comm/pyaudio_helper/interactive_widgets.py
sk_dsp_comm/pyaudio_helper/pyaudio_helper.py
sk_dsp_comm/pyaudio_helper/test/__init__.py
sk_dsp_comm/pyaudio_helper/test/test_imports.py
pyaudio_helper-1.1.2.dist-info/LICENSE
pyaudio_helper-1.1.2.dist-info/METADATA
pyaudio_helper-1.1.2.dist-info/WHEEL
pyaudio_helper-1.1.2.dist-info/top_level.txt
pyaudio_helper-1.1.2.dist-info/RECORD
