Metadata-Version: 2.1
Name: pyaudio-helper
Version: 1.1.2
Summary: PyAudio Helper
Home-page: https://github.com/scikit-dsp-comm/pyaudio_helper
Author: Mark Wickert
Author-email: mwickert@uccs.edu
Maintainer: Chiranth Siddappa
Maintainer-email: chiranthsiddappa@gmail.com
License: BSD
Platform: UNKNOWN
Requires-Python: >=3.5
License-File: LICENSE
Requires-Dist: matplotlib
Requires-Dist: numpy
Requires-Dist: pyaudio
Requires-Dist: setuptools (>=40.1.0)
Provides-Extra: extras
Requires-Dist: ipywidgets (<8,>=7.6.4) ; extra == 'extras'
